odoo/addons/project_template_milestone/README.rst
odoo/addons/project_template_milestone/__init__.py
odoo/addons/project_template_milestone/__manifest__.py
odoo/addons/project_template_milestone/i18n/de.po
odoo/addons/project_template_milestone/i18n/es.po
odoo/addons/project_template_milestone/i18n/it.po
odoo/addons/project_template_milestone/i18n/project_template_milestone.pot
odoo/addons/project_template_milestone/i18n/pt.po
odoo/addons/project_template_milestone/i18n/pt_BR.po
odoo/addons/project_template_milestone/i18n/sl.po
odoo/addons/project_template_milestone/models/__init__.py
odoo/addons/project_template_milestone/models/project.py
odoo/addons/project_template_milestone/readme/CONTRIBUTORS.rst
odoo/addons/project_template_milestone/readme/DESCRIPTION.rst
odoo/addons/project_template_milestone/readme/USAGE.rst
odoo/addons/project_template_milestone/static/description/icon.png
odoo/addons/project_template_milestone/static/description/index.html
odoo/addons/project_template_milestone/tests/__init__.py
odoo/addons/project_template_milestone/tests/test_project_template.py
odoo14_addon_project_template_milestone-14.0.1.0.1.dev13.dist-info/METADATA
odoo14_addon_project_template_milestone-14.0.1.0.1.dev13.dist-info/WHEEL
odoo14_addon_project_template_milestone-14.0.1.0.1.dev13.dist-info/top_level.txt
odoo14_addon_project_template_milestone-14.0.1.0.1.dev13.dist-info/RECORD
