Metadata-Version: 2.1
Name: odoo14-addon-project_template_milestone
Version: 14.0.1.0.1.dev13
Summary: Adds function to copy of milestones when creating a project from template
Home-page: https://github.com/OCA/project
Author: Patrick Wilson, Odoo Community Association (OCA),Open Source Integrators
Author-email: support@odoo-community.org
License: AGPL-3
Classifier: Programming Language :: Python
Classifier: Framework :: Odoo
Classifier: Framework :: Odoo :: 14.0
Classifier: License :: OSI Approved :: GNU Affero General Public License v3
Classifier: Development Status :: 4 - Beta
Requires-Python: >=3.6
Requires-Dist: odoo14-addon-project-milestone
Requires-Dist: odoo14-addon-project-template
Requires-Dist: odoo<14.1dev,>=14.0a
